{"cameraMode":{"drawMode":0,"name":"Shaded","section":"Shading Mode"},"sceneLighting":true,"audioPlay":false,"sceneViewState":{"m_AlwaysRefresh":false,"showFog":true,"showSkybox":true,"showFlares":true,"showImageEffects":true,"showParticleSystems":true,"showVisualEffectGraphs":true,"m_FxEnabled":true},"in2DMode":false,"pivot":{"x":-545.222900390625,"y":49.55803680419922,"z":32.41928482055664},"rotation":{"x":0.031228821724653245,"y":-0.7770983576774597,"z":0.03494402766227722,"w":0.6281648874282837},"size":122.27238464355469,"orthographic":false}